{
  "type": "spirit:transmutation",
  "activatorIngredient": {
    "item": "minecraft:netherite_leggings"
  },
  "entityIngredients": [],
  "ingredients": [
    {
      "item": "spirit:soul_steel_ingot"
    },
    {
      "item": "spirit:soul_steel_ingot"
    },
    {
      "item": "spirit:soul_steel_ingot"
    },
    {
      "item": "spirit:soul_steel_ingot"
    },
    {
      "item": "spirit:crystal_shard"
    },
    {
      "item": "spirit:crystal_shard"
    },
    {
      "item": "spirit:crystal_shard"
    },
    {
      "item": "spirit:crystal_shard"
    }
  ],
  "result":  "spirit:soul_steel_leggings"
}